{"SKxttKGl3QlPMIZMESxhWQ==":"spa-gift-vouchers-1170x539.jpg","D6osQr0R2Hf7QaMLWyg5NA==":"nirvelli-med-spa-and-laser-massage-therapy.jpg","A4YVS7YSdiZd9zDtfgYoRw==":"banner-procedures.2e16d0ba.fill-800x600.jpg","9KqXo+iY6spsEcj7qPBOTw==":"facial-86487979.jpg","DyQ4qKjq53dOY5IlQ92TXQ==":"spa-menu.webp","4LqxRFxn9YUW2AAJgHqjsA==":"manicure-and-pedicure-768x384-1.jpg","COj/aazYUqzetDXy4jpo9Q==":"c15dbb7776cb38219805ce96757c74f3-xl.jpg","8yoxfZzFN4OtDj/3DAIRqA==":"capture.png","n/rc2Nnu919WSL05S2CccQ==":"capture-1.png"}